fpl/__init__.py
fpl/cli.py
fpl/constants.py
fpl/core.py
fpl/utils.py
fpl_test-0.5.4.dist-info/LICENSE.txt
fpl_test-0.5.4.dist-info/METADATA
fpl_test-0.5.4.dist-info/WHEEL
fpl_test-0.5.4.dist-info/entry_points.txt
fpl_test-0.5.4.dist-info/top_level.txt
fpl_test-0.5.4.dist-info/RECORD
