Metadata-Version: 2.1
Name: fpl-test
Version: 0.5.4
Summary: A Python wrapper for the Fantasy Premier League API
Home-page: https://github.com/amosbastian/fpl
Author: emre yilmaz
Author-email: mail@emreyilmaz.me
License: MIT
Project-URL: Documentation, http://fpl.readthedocs.io/en/latest/
Project-URL: Source, https://github.com/amosbastian/fpl
Keywords: fpl fantasy premier league
Platform: UNKNOWN
Classifier: Development Status :: 4 - Beta
Classifier: Intended Audience :: Developers
Classifier: License :: OSI Approved :: MIT License
Classifier: Programming Language :: Python :: 2.7
Classifier: Programming Language :: Python :: 3.3
Classifier: Programming Language :: Python :: 3.4
Classifier: Programming Language :: Python :: 3.5
Classifier: Programming Language :: Python :: 3.6
Requires-Dist: Click
Requires-Dist: colorama
Requires-Dist: PTable
Requires-Dist: requests
